MANIFEST.in
README.rst
setup.py
collective/__init__.py
collective/__init__.pyc
collective.js.chatbox.egg-info/PKG-INFO
collective.js.chatbox.egg-info/SOURCES.txt
collective.js.chatbox.egg-info/dependency_links.txt
collective.js.chatbox.egg-info/entry_points.txt
collective.js.chatbox.egg-info/namespace_packages.txt
collective.js.chatbox.egg-info/not-zip-safe
collective.js.chatbox.egg-info/requires.txt
collective.js.chatbox.egg-info/top_level.txt
collective/js/__init__.py
collective/js/__init__.pyc
collective/js/chatbox/__init__.py
collective/js/chatbox/__init__.pyc
collective/js/chatbox/configure.zcml
collective/js/chatbox/profiles/default/cssregistry.xml
collective/js/chatbox/profiles/default/jsregistry.xml
collective/js/chatbox/profiles/default/metadata.xml
collective/js/chatbox/resources/jquery.ui.chatbox.css
collective/js/chatbox/resources/jquery.ui.chatbox.js
docs/HISTORY.txt