Metadata-Version: 1.1
Name: collective.js.chatbox
Version: 1.0
Summary: A packaging of the jQuery UI Chatbox plugin for Plone
Home-page: https://github.com/collective/collective.js.chatbox
Author: UNKNOWN
Author-email: UNKNOWN
License: MIT
Platform: UNKNOWN
Classifier: Programming Language :: Python
